dlercloud/__init__.py
dlercloud/api.py
dlercloud/exceptions.py
dlercloud/models.py
tests/__init__.py
tests/test_api.py
dlercloud-0.0.8.dist-info/LICENSE
dlercloud-0.0.8.dist-info/METADATA
dlercloud-0.0.8.dist-info/WHEEL
dlercloud-0.0.8.dist-info/top_level.txt
dlercloud-0.0.8.dist-info/RECORD
