Metadata-Version: 2.1
Name: dlercloud
Version: 0.0.8
Summary: A Python Wrapper for DlerCloud API
Home-page: https://github.com/youfou/dlercloud
Author: Youfou
Author-email: youfouzz@gmail.com
License: UNKNOWN
Keywords: DlerCloud
Platform: UNKNOWN
Classifier: Programming Language :: Python :: 3
Classifier: License :: OSI Approved :: MIT License
Classifier: Operating System :: OS Independent
Requires-Dist: requests
